colp/__init__.py
colp/conversion.py
colp/lang.py
colp-0.0.2.data/scripts/colp
test/__init__.py
test/test.py
colp-0.0.2.dist-info/LICENSE
colp-0.0.2.dist-info/METADATA
colp-0.0.2.dist-info/WHEEL
colp-0.0.2.dist-info/top_level.txt
colp-0.0.2.dist-info/RECORD
