Metadata-Version: 2.1
Name: colp
Version: 0.0.2
Summary: Color Processor
Home-page: https://github.com/mvrozanti/colp
Author: Marcelo V. Rozanti
Author-email: mvrozanti@hotmail.com
License: UNKNOWN
Platform: UNKNOWN
Classifier: Development Status :: 4 - Beta
Classifier: Topic :: Artistic Software
Classifier: Intended Audience :: Developers
Classifier: Programming Language :: Python :: 3.4
Classifier: Programming Language :: Python :: 3.5
Classifier: Programming Language :: Python :: 3.6
Classifier: Programming Language :: Python :: 3 :: Only
